{
  "kind": "collectionType",
  "collectionName": "embeddings",
  "info": {
    "singularName": "embedding",
    "pluralName": "embeddings",
    "displayName": "embedding "
  },
  "options": {
    "draftAndPublish": false
  },
  "pluginOptions": {
    "content-manager": {
      "visible": true
    },
    "content-type-builder": {
      "visible": false
    }
  },
  "attributes": {
    "title": {
      "type": "string"
    },
    "content": {
      "type": "richtext"
    },
    "embeddings": {
      "type": "json"
    }
  }
}
